{
    "1058804764": {
        "id": "1058804764",
        "username": "lupaminum",
        "status": "free",
        "is_banned": 0,
        "last_fix": 0,
        "fix_limit": 0,
        "referral_points": 0,
        "referred_by": null,
        "join_date": "2026-02-02T07:53:01.560Z"
    },
    "1452168435": {
        "id": "1452168435",
        "username": "ZarMoroz",
        "status": "free",
        "is_banned": 0,
        "last_fix": 0,
        "fix_limit": 0,
        "referral_points": 0,
        "referred_by": null,
        "join_date": "2026-02-09T07:55:35.167Z"
    },
    "1629801625": {
        "id": "1629801625",
        "username": "dioarsk1e",
        "status": "free",
        "is_banned": 0,
        "last_fix": 0,
        "fix_limit": 0,
        "referral_points": 0,
        "referred_by": null,
        "join_date": "2026-02-02T03:36:22.380Z"
    },
    "1860883643": {
        "id": "1860883643",
        "username": "Yazxx0FC",
        "status": "free",
        "is_banned": 0,
        "last_fix": 0,
        "fix_limit": 0,
        "referral_points": 0,
        "referred_by": null,
        "join_date": "2026-02-01T00:37:39.158Z"
    },
    "1964793201": {
        "id": "1964793201",
        "username": "Amoy860",
        "status": "free",
        "is_banned": 0,
        "last_fix": 0,
        "fix_limit": 0,
        "referral_points": 0,
        "referred_by": null,
        "join_date": "2026-02-02T08:12:35.917Z"
    },
    "6640208369": {
        "id": "6640208369",
        "username": "YazxxOFC",
        "status": "owner",
        "is_banned": 0,
        "last_fix": 0,
        "fix_limit": 0,
        "referral_points": 0,
        "referred_by": null,
        "join_date": "2026-01-31T16:25:26.365Z"
    },
    "8533948592": {
        "id": "8533948592",
        "username": "Ihhserem12",
        "status": "free",
        "is_banned": 0,
        "last_fix": 0,
        "fix_limit": 0,
        "referral_points": 0,
        "referred_by": null,
        "join_date": "2026-02-01T00:38:35.943Z"
    },
    "7942136966": {
        "id": "7942136966",
        "username": "⏤͟͞𝐍𝐀𝐔𝐑𝐀 | 𝐎𝐅𝐅𝐅𝐈𝐂𝐈𝐀𝐋",
        "status": "free",
        "is_banned": 0,
        "last_fix": 0,
        "fix_limit": 0,
        "referral_points": 0,
        "referred_by": null,
        "join_date": "2026-02-01T02:27:34.726Z"
    },
    "8412573950": {
        "id": "8412573950",
        "username": "Daxaa37",
        "status": "free",
        "is_banned": 0,
        "last_fix": 0,
        "fix_limit": 0,
        "referral_points": 0,
        "referred_by": null,
        "join_date": "2026-02-01T14:35:27.985Z"
    },
    "6915520273": {
        "id": "6915520273",
        "username": "rakanchn",
        "status": "free",
        "is_banned": 0,
        "last_fix": 0,
        "fix_limit": 0,
        "referral_points": 0,
        "referred_by": null,
        "join_date": "2026-02-01T14:39:14.865Z"
    },
    "8416791008": {
        "id": "8416791008",
        "username": "KallJasJus",
        "status": "free",
        "is_banned": 0,
        "last_fix": 0,
        "fix_limit": 0,
        "referral_points": 0,
        "referred_by": null,
        "join_date": "2026-02-01T14:45:27.208Z"
    },
    "8337133110": {
        "id": "8337133110",
        "username": "Alaman729",
        "status": "free",
        "is_banned": 0,
        "last_fix": 0,
        "fix_limit": 0,
        "referral_points": 0,
        "referred_by": null,
        "join_date": "2026-02-01T14:54:56.964Z"
    },
    "8316938512": {
        "id": "8316938512",
        "username": "MAMAN",
        "status": "free",
        "is_banned": 0,
        "last_fix": 0,
        "fix_limit": 0,
        "referral_points": 0,
        "referred_by": null,
        "join_date": "2026-02-01T15:04:34.147Z"
    },
    "6704771517": {
        "id": "6704771517",
        "username": "FAAkVIP",
        "status": "free",
        "is_banned": 0,
        "last_fix": 0,
        "fix_limit": 0,
        "referral_points": 0,
        "referred_by": null,
        "join_date": "2026-02-01T15:28:20.443Z"
    },
    "7100430728": {
        "id": "7100430728",
        "username": "Alexnaomiz",
        "status": "free",
        "is_banned": 0,
        "last_fix": 0,
        "fix_limit": 0,
        "referral_points": 0,
        "referred_by": null,
        "join_date": "2026-02-01T16:26:41.791Z"
    },
    "8585288024": {
        "id": "8585288024",
        "username": "alok",
        "status": "free",
        "is_banned": 0,
        "last_fix": 0,
        "fix_limit": 0,
        "referral_points": 0,
        "referred_by": null,
        "join_date": "2026-02-01T17:25:23.194Z"
    },
    "6692741789": {
        "id": "6692741789",
        "username": "LinggihDT",
        "status": "free",
        "is_banned": 0,
        "last_fix": 0,
        "fix_limit": 0,
        "referral_points": 0,
        "referred_by": null,
        "join_date": "2026-02-01T18:08:23.484Z"
    },
    "8208549093": {
        "id": "8208549093",
        "username": "ulzz_2",
        "status": "free",
        "is_banned": 0,
        "last_fix": 0,
        "fix_limit": 0,
        "referral_points": 0,
        "referred_by": null,
        "join_date": "2026-02-01T23:57:15.064Z"
    },
    "7214437193": {
        "id": "7214437193",
        "username": "TODOTHEGOOD",
        "status": "free",
        "is_banned": 0,
        "last_fix": 0,
        "fix_limit": 0,
        "referral_points": 0,
        "referred_by": null,
        "join_date": "2026-02-02T01:41:35.842Z"
    },
    "8219984852": {
        "id": "8219984852",
        "username": "Toko_Markzilham",
        "status": "free",
        "is_banned": 0,
        "last_fix": 0,
        "fix_limit": 0,
        "referral_points": 0,
        "referred_by": null,
        "join_date": "2026-02-02T05:42:16.224Z"
    },
    "7575136006": {
        "id": "7575136006",
        "username": "padukarezz",
        "status": "free",
        "is_banned": 0,
        "last_fix": 0,
        "fix_limit": 0,
        "referral_points": 0,
        "referred_by": null,
        "join_date": "2026-02-02T05:43:53.029Z"
    },
    "8396384015": {
        "id": "8396384015",
        "username": "Rilll15",
        "status": "free",
        "is_banned": 0,
        "last_fix": 0,
        "fix_limit": 0,
        "referral_points": 0,
        "referred_by": null,
        "join_date": "2026-02-02T06:33:18.862Z"
    },
    "7913127127": {
        "id": "7913127127",
        "username": "anomaliboss999",
        "status": "free",
        "is_banned": 0,
        "last_fix": 0,
        "fix_limit": 0,
        "referral_points": 0,
        "referred_by": null,
        "join_date": "2026-02-02T07:07:50.013Z"
    },
    "8031977477": {
        "id": "8031977477",
        "username": "ramaz123",
        "status": "free",
        "is_banned": 0,
        "last_fix": 0,
        "fix_limit": 0,
        "referral_points": 0,
        "referred_by": null,
        "join_date": "2026-02-02T07:08:55.258Z"
    },
    "6598277525": {
        "id": "6598277525",
        "username": "Ren969_0",
        "status": "free",
        "is_banned": 0,
        "last_fix": 0,
        "fix_limit": 0,
        "referral_points": 0,
        "referred_by": null,
        "join_date": "2026-02-02T07:10:35.028Z"
    },
    "8304747033": {
        "id": "8304747033",
        "username": "Inonlyfloren",
        "status": "free",
        "is_banned": 0,
        "last_fix": 0,
        "fix_limit": 0,
        "referral_points": 0,
        "referred_by": null,
        "join_date": "2026-02-02T07:13:23.605Z"
    },
    "8550214984": {
        "id": "8550214984",
        "username": "jualangcbyarchv",
        "status": "free",
        "is_banned": 0,
        "last_fix": 0,
        "fix_limit": 0,
        "referral_points": 0,
        "referred_by": null,
        "join_date": "2026-02-02T07:22:41.152Z"
    },
    "8477553361": {
        "id": "8477553361",
        "username": "dimsummentaienakwoii",
        "status": "free",
        "is_banned": 0,
        "last_fix": 0,
        "fix_limit": 0,
        "referral_points": 0,
        "referred_by": null,
        "join_date": "2026-02-02T07:23:42.919Z"
    },
    "6815446368": {
        "id": "6815446368",
        "username": "ikyyzzy",
        "status": "free",
        "is_banned": 0,
        "last_fix": 0,
        "fix_limit": 0,
        "referral_points": 0,
        "referred_by": null,
        "join_date": "2026-02-02T07:24:59.120Z"
    },
    "7667558762": {
        "id": "7667558762",
        "username": "natzkoboy_14",
        "status": "free",
        "is_banned": 0,
        "last_fix": 0,
        "fix_limit": 0,
        "referral_points": 0,
        "referred_by": null,
        "join_date": "2026-02-02T07:31:17.499Z"
    },
    "8425285509": {
        "id": "8425285509",
        "username": "Prionovandananda94",
        "status": "free",
        "is_banned": 0,
        "last_fix": 0,
        "fix_limit": 0,
        "referral_points": 0,
        "referred_by": null,
        "join_date": "2026-02-02T07:36:09.621Z"
    },
    "8233823267": {
        "id": "8233823267",
        "username": "koplex_stecu",
        "status": "free",
        "is_banned": 0,
        "last_fix": 0,
        "fix_limit": 0,
        "referral_points": 0,
        "referred_by": null,
        "join_date": "2026-02-02T07:41:09.339Z"
    },
    "7672559319": {
        "id": "7672559319",
        "username": "Bara",
        "status": "free",
        "is_banned": 0,
        "last_fix": 0,
        "fix_limit": 0,
        "referral_points": 0,
        "referred_by": null,
        "join_date": "2026-02-02T07:54:34.154Z"
    },
    "6814299327": {
        "id": "6814299327",
        "username": "YannnTJ",
        "status": "free",
        "is_banned": 0,
        "last_fix": 0,
        "fix_limit": 0,
        "referral_points": 0,
        "referred_by": null,
        "join_date": "2026-02-02T07:54:46.267Z"
    },
    "8471608367": {
        "id": "8471608367",
        "username": "Febbzzz01",
        "status": "free",
        "is_banned": 0,
        "last_fix": 0,
        "fix_limit": 0,
        "referral_points": 0,
        "referred_by": null,
        "join_date": "2026-02-02T08:03:04.297Z"
    },
    "7108017960": {
        "id": "7108017960",
        "username": "ekasss01",
        "status": "free",
        "is_banned": 0,
        "last_fix": 0,
        "fix_limit": 0,
        "referral_points": 0,
        "referred_by": null,
        "join_date": "2026-02-02T08:16:42.816Z"
    },
    "6695043948": {
        "id": "6695043948",
        "username": "yukeeajaaaaaaa",
        "status": "free",
        "is_banned": 0,
        "last_fix": 0,
        "fix_limit": 0,
        "referral_points": 0,
        "referred_by": null,
        "join_date": "2026-02-02T08:22:45.683Z"
    },
    "8521518225": {
        "id": "8521518225",
        "username": "PENYEPONG",
        "status": "free",
        "is_banned": 0,
        "last_fix": 0,
        "fix_limit": 0,
        "referral_points": 0,
        "referred_by": null,
        "join_date": "2026-02-02T08:53:00.238Z"
    },
    "8018842007": {
        "id": "8018842007",
        "username": "cihuyx1",
        "status": "free",
        "is_banned": 0,
        "last_fix": 0,
        "fix_limit": 0,
        "referral_points": 0,
        "referred_by": null,
        "join_date": "2026-02-02T09:09:19.795Z"
    },
    "8521215217": {
        "id": "8521215217",
        "username": "Genzi8282",
        "status": "free",
        "is_banned": 0,
        "last_fix": 0,
        "fix_limit": 0,
        "referral_points": 0,
        "referred_by": null,
        "join_date": "2026-02-02T09:19:46.835Z"
    },
    "7615041138": {
        "id": "7615041138",
        "username": "kyy",
        "status": "free",
        "is_banned": 0,
        "last_fix": 0,
        "fix_limit": 0,
        "referral_points": 0,
        "referred_by": null,
        "join_date": "2026-02-02T09:44:15.018Z"
    },
    "8538723253": {
        "id": "8538723253",
        "username": "Zen",
        "status": "free",
        "is_banned": 0,
        "last_fix": 0,
        "fix_limit": 0,
        "referral_points": 0,
        "referred_by": null,
        "join_date": "2026-02-02T09:45:58.687Z"
    },
    "6876331554": {
        "id": "6876331554",
        "username": "fanzeboy",
        "status": "free",
        "is_banned": 0,
        "last_fix": 0,
        "fix_limit": 0,
        "referral_points": 0,
        "referred_by": null,
        "join_date": "2026-02-02T09:48:47.983Z"
    },
    "8441794215": {
        "id": "8441794215",
        "username": "riskihosting",
        "status": "free",
        "is_banned": 0,
        "last_fix": 0,
        "fix_limit": 0,
        "referral_points": 0,
        "referred_by": null,
        "join_date": "2026-02-02T10:19:30.672Z"
    },
    "6352331823": {
        "id": "6352331823",
        "username": "Syakirrwok",
        "status": "free",
        "is_banned": 0,
        "last_fix": 0,
        "fix_limit": 0,
        "referral_points": 0,
        "referred_by": null,
        "join_date": "2026-02-02T10:31:37.402Z"
    },
    "5540503836": {
        "id": "5540503836",
        "username": "sistecu15",
        "status": "free",
        "is_banned": 0,
        "last_fix": 0,
        "fix_limit": 0,
        "referral_points": 0,
        "referred_by": null,
        "join_date": "2026-02-02T11:29:40.656Z"
    },
    "8200120849": {
        "id": "8200120849",
        "username": "Zaki",
        "status": "free",
        "is_banned": 0,
        "last_fix": 0,
        "fix_limit": 0,
        "referral_points": 0,
        "referred_by": null,
        "join_date": "2026-02-02T13:16:36.303Z"
    },
    "7345716549": {
        "id": "7345716549",
        "username": "CYYBEDMOD",
        "status": "free",
        "is_banned": 0,
        "last_fix": 0,
        "fix_limit": 0,
        "referral_points": 0,
        "referred_by": null,
        "join_date": "2026-02-07T02:38:56.433Z"
    },
    "7738193502": {
        "id": "7738193502",
        "username": "wkhem92",
        "status": "free",
        "is_banned": 0,
        "last_fix": 0,
        "fix_limit": 0,
        "referral_points": 0,
        "referred_by": null,
        "join_date": "2026-02-07T04:07:13.739Z"
    },
    "7550197989": {
        "id": "7550197989",
        "username": "MaffCihuy",
        "status": "free",
        "is_banned": 0,
        "last_fix": 0,
        "fix_limit": 0,
        "referral_points": 0,
        "referred_by": null,
        "join_date": "2026-02-07T04:08:31.229Z"
    },
    "6742086334": {
        "id": "6742086334",
        "username": "SERPAYYY",
        "status": "free",
        "is_banned": 0,
        "last_fix": 0,
        "fix_limit": 0,
        "referral_points": 0,
        "referred_by": null,
        "join_date": "2026-02-07T10:01:21.760Z"
    },
    "8420168168": {
        "id": "8420168168",
        "username": "daffaaa_ajaa2",
        "status": "free",
        "is_banned": 0,
        "last_fix": 0,
        "fix_limit": 0,
        "referral_points": 0,
        "referred_by": null,
        "join_date": "2026-02-07T15:40:42.628Z"
    },
    "8319909523": {
        "id": "8319909523",
        "username": "Halo",
        "status": "free",
        "is_banned": 0,
        "last_fix": 0,
        "fix_limit": 0,
        "referral_points": 0,
        "referred_by": null,
        "join_date": "2026-02-08T01:53:09.778Z"
    },
    "6324900045": {
        "id": "6324900045",
        "username": "moraxjun",
        "status": "free",
        "is_banned": 0,
        "last_fix": 0,
        "fix_limit": 0,
        "referral_points": 0,
        "referred_by": null,
        "join_date": "2026-02-08T13:28:42.587Z"
    },
    "8358398350": {
        "id": "8358398350",
        "username": "rikahigurashi",
        "status": "free",
        "is_banned": 0,
        "last_fix": 0,
        "fix_limit": 0,
        "referral_points": 0,
        "referred_by": null,
        "join_date": "2026-02-08T13:30:26.675Z"
    },
    "8536410355": {
        "id": "8536410355",
        "username": "⏤͟͟͞͞𝟒𝟒𝟒 タзвезда≠",
        "status": "free",
        "is_banned": 0,
        "last_fix": 0,
        "fix_limit": 0,
        "referral_points": 0,
        "referred_by": null,
        "join_date": "2026-02-08T14:02:51.687Z"
    },
    "8552765707": {
        "id": "8552765707",
        "username": "raxy",
        "status": "free",
        "is_banned": 0,
        "last_fix": 0,
        "fix_limit": 0,
        "referral_points": 0,
        "referred_by": null,
        "join_date": "2026-02-08T15:06:12.510Z"
    },
    "8131024942": {
        "id": "8131024942",
        "username": "valconz",
        "status": "free",
        "is_banned": 0,
        "last_fix": 0,
        "fix_limit": 0,
        "referral_points": 0,
        "referred_by": null,
        "join_date": "2026-02-08T22:26:25.466Z"
    },
    "7453587730": {
        "id": "7453587730",
        "username": "piwwh2r",
        "status": "free",
        "is_banned": 0,
        "last_fix": 0,
        "fix_limit": 0,
        "referral_points": 0,
        "referred_by": null,
        "join_date": "2026-02-09T00:44:44.145Z"
    },
    "8490275449": {
        "id": "8490275449",
        "username": "Ikyyy",
        "status": "free",
        "is_banned": 0,
        "last_fix": 0,
        "fix_limit": 0,
        "referral_points": 0,
        "referred_by": null,
        "join_date": "2026-02-09T00:47:54.220Z"
    },
    "8245673882": {
        "id": "8245673882",
        "username": "michael",
        "status": "free",
        "is_banned": 0,
        "last_fix": 0,
        "fix_limit": 0,
        "referral_points": 0,
        "referred_by": null,
        "join_date": "2026-02-09T01:51:32.892Z"
    },
    "6473821898": {
        "id": "6473821898",
        "username": "Lucyanaxx",
        "status": "free",
        "is_banned": 0,
        "last_fix": 0,
        "fix_limit": 0,
        "referral_points": 0,
        "referred_by": null,
        "join_date": "2026-02-09T02:37:02.489Z"
    },
    "7511061771": {
        "id": "7511061771",
        "username": "haruko_dev",
        "status": "free",
        "is_banned": 0,
        "last_fix": 0,
        "fix_limit": 0,
        "referral_points": 0,
        "referred_by": null,
        "join_date": "2026-02-09T02:56:53.965Z"
    },
    "8203369302": {
        "id": "8203369302",
        "username": "Damar",
        "status": "free",
        "is_banned": 0,
        "last_fix": 0,
        "fix_limit": 0,
        "referral_points": 0,
        "referred_by": null,
        "join_date": "2026-02-09T03:25:18.053Z"
    },
    "7313166199": {
        "id": "7313166199",
        "username": "VeroSikma",
        "status": "free",
        "is_banned": 0,
        "last_fix": 0,
        "fix_limit": 0,
        "referral_points": 0,
        "referred_by": null,
        "join_date": "2026-02-09T06:21:42.428Z"
    },
    "8592142360": {
        "id": "8592142360",
        "username": "Paang",
        "status": "free",
        "is_banned": 0,
        "last_fix": 0,
        "fix_limit": 0,
        "referral_points": 0,
        "referred_by": null,
        "join_date": "2026-02-09T07:19:48.568Z"
    },
    "8534787615": {
        "id": "8534787615",
        "username": "Gatauoyi",
        "status": "free",
        "is_banned": 0,
        "last_fix": 0,
        "fix_limit": 0,
        "referral_points": 0,
        "referred_by": null,
        "join_date": "2026-02-09T08:01:53.337Z"
    },
    "7491855686": {
        "id": "7491855686",
        "username": "Kokseamryam",
        "status": "free",
        "is_banned": 0,
        "last_fix": 0,
        "fix_limit": 0,
        "referral_points": 0,
        "referred_by": null,
        "join_date": "2026-02-09T08:10:37.264Z"
    }
}